age_community_detection/Check.py
age_community_detection/Exception.py
age_community_detection/Graph.py
age_community_detection/Lib.py
age_community_detection/VERSION.py
age_community_detection/__init__.py
age_community_detection/lib/library.dll
age_community_detection/lib/library.so
apache_age_community_detection-0.1.4.dist-info/LICENSE
apache_age_community_detection-0.1.4.dist-info/METADATA
apache_age_community_detection-0.1.4.dist-info/WHEEL
apache_age_community_detection-0.1.4.dist-info/top_level.txt
apache_age_community_detection-0.1.4.dist-info/RECORD
